sp_obs/__init__.py
sp_obs/billing.py
sp_obs/tag.py
sp_obs/utils.py
sp_obs/_internal/__init__.py
sp_obs/_internal/config.py
sp_obs/_internal/constants.py
sp_obs/_internal/exporter.py
sp_obs/_internal/processor.py
sp_obs/_internal/scrubbing.py
sp_obs/_internal/tracer.py
sp_obs/_internal/core/__init__.py
sp_obs/_internal/core/recognised_integrations.py
sp_obs/_internal/core/aiohttp/__init__.py
sp_obs/_internal/core/aiohttp/aiohttp.py
sp_obs/_internal/core/grpc/__init__.py
sp_obs/_internal/core/grpc/grpc.py
sp_obs/_internal/core/grpc/grpc_aio.py
sp_obs/_internal/core/grpc/grpc_integrations.py
sp_obs/_internal/core/grpc/grpc_utils.py
sp_obs/_internal/core/httpx/__init__.py
sp_obs/_internal/core/httpx/async_stream.py
sp_obs/_internal/core/httpx/httpx.py
sp_obs/_internal/core/httpx/sync_stream.py
sp_obs/_internal/core/providers/__init__.py
sp_obs/_internal/core/providers/anthropic.py
sp_obs/_internal/core/providers/base.py
sp_obs/_internal/core/providers/deepgram.py
sp_obs/_internal/core/providers/elevenlabs.py
sp_obs/_internal/core/providers/firecrawl.py
sp_obs/_internal/core/providers/mistral.py
sp_obs/_internal/core/providers/openai.py
sp_obs/_internal/core/providers/perplexity.py
sp_obs/_internal/core/providers/scrapingbee.py
sp_obs/_internal/core/providers/serpapi.py
sp_obs/_internal/core/providers/vertexai.py
sp_obs/_internal/core/providers/voyageai.py
sp_obs/_internal/core/requests/__init__.py
sp_obs/_internal/core/requests/requests.py
sp_obs-0.5.3.dist-info/METADATA
sp_obs-0.5.3.dist-info/WHEEL
sp_obs-0.5.3.dist-info/licenses/LICENSE
sp_obs-0.5.3.dist-info/RECORD
