Metadata-Version: 2.4
Name: sp-obs
Version: 0.5.3
Summary: Observability integration with Spinal
Project-URL: Homepage, https://github.com/withspinal/sp-obs
Project-URL: Issues, https://github.com/withspinal/sp-obs/issues
Author-email: Andrew van Rensburg <andrew@withspinal.com>
License-Expression: MIT
License-File: LICENSE
Keywords: ai,llm,monitoring,observability,opentelemetry,spinal,tracing
Classifier: Development Status :: 4 - Beta
Classifier: Intended Audience :: Developers
Classifier: License :: OSI Approved :: MIT License
Classifier: Programming Language :: Python :: 3
Classifier: Programming Language :: Python :: 3.11
Classifier: Programming Language :: Python :: 3.12
Classifier: Programming Language :: Python :: 3.13
Classifier: Topic :: Software Development :: Libraries :: Python Modules
Classifier: Topic :: System :: Monitoring
Requires-Python: >=3.11
Requires-Dist: aiohttp>=3.13.0
Requires-Dist: grpcio<2,>=1.68.1
Requires-Dist: httpx<1.0.0,>=0.28.0
Requires-Dist: opentelemetry-api<2,>=1.38.0
Requires-Dist: opentelemetry-instrumentation-aiohttp-client>=0.58b0
Requires-Dist: opentelemetry-instrumentation-grpc>=0.59b0
Requires-Dist: opentelemetry-instrumentation-httpx<1,>=0.57b0
Requires-Dist: opentelemetry-instrumentation-requests<1,>=0.57b0
Requires-Dist: opentelemetry-sdk<2,>=1.38.0
Requires-Dist: opentelemetry-semantic-conventions-ai>=0.4.12
Requires-Dist: orjson<4,>=3.11.1
